{"hash":"aa5a7ff62b399012289acf12f7cc1503ba4e22e5","data":{"post":{"title":"Как установить Gradle на Mac OS","content":"\n## Скачиваем бинарный дистрибутив\n\nНеобходимо перейти на url: [gradle.org/releases/](https://gradle.org/releases/) и скачивать дистрибутив для последней версии Gradle.\n\n## Извлекаем архив\n\n```bash\ncd /Library/\nmkdir /Gradle/\nunzip gradle-6.3-bin.zip\n```\n\n## Настраиваем переменные окружения\n\n1. Открыть на редактирование файл `.profile`\n\n```bash\nnano ~/.profile\n```\n\n2. В конец добавляем строчки\n\n```bash\nexport GRADLE_HOME=/Library/Gradle/gradle-6.3\nexport PATH=$PATH:$GRADLE_HOME/bin\n```\n\n3. Нажимаем `Ctrl+X` и соглашаемся с сохранением изменений, нажав на `Y`\n4. Выполняем команду для инициализации изменений и проверяем что переменная среды выводится верно\n\n```bash\nsource ~/.profile\necho $JAVA_HOME\necho $PATH\n```\n\n4. Теперь нужно перезапустить консоль и проверить версию Java\n\n```bash\njava -version\n```\n","description":"Устанавливаем Gradle локально на ПК с MacOS","image":"null","category":{"id":"automation","title":"automation","path":"/category/automation/"},"date":"02/05/2020","path":"/kak-ustanovit-gradle-na-mac-os/","links":[{"title":"","items":[{"title":"Как установить OpenJDK на Mac OS","link":"/kak-ustanovit-open-jdk-na-mac-os/"}]}],"headings":[{"value":"Скачиваем бинарный дистрибутив","anchor":"#скачиваем-бинарный-дистрибутив"},{"value":"Извлекаем архив","anchor":"#извлекаем-архив"},{"value":"Настраиваем переменные окружения","anchor":"#настраиваем-переменные-окружения"}],"subtitles":[{"depth":2,"value":"Скачиваем бинарный дистрибутив","anchor":"#скачиваем-бинарный-дистрибутив"},{"depth":2,"value":"Извлекаем архив","anchor":"#извлекаем-архив"},{"depth":2,"value":"Настраиваем переменные окружения","anchor":"#настраиваем-переменные-окружения"}],"tags":[{"id":"gradle","title":"gradle","path":"/tag/gradle/"},{"id":"setup","title":"setup","path":"/tag/setup/"},{"id":"macos","title":"macos","path":"/tag/macos/"}]},"comments":{"edges":[]}},"context":{}}