{"hash":"7ce6058f470c3851afaa44882541a7f3d1089ffc","data":{"category":{"title":"python","path":"/category/python/","belongsTo":{"totalCount":1,"pageInfo":{"totalPages":1,"currentPage":1},"edges":[{"node":{"id":"0308218cf04369446cf88825234a8605","title":"Введение","content":"\n## Введение\n\n\nпервый урок","date":"2025-07-16T00:00:00.000Z","icon":"fas fa-code","image":"null","path":"/vvedenie/","order":1,"category":{"title":"python","path":"/category/python/"},"tags":[{"title":"algorithms","path":"/tag/algorithms/"},{"title":"python","path":"/tag/python/"},{"title":"алгоритмы","path":"/tag/%D0%B0%D0%BB%D0%B3%D0%BE%D1%80%D0%B8%D1%82%D0%BC%D1%8B/"}],"headings":[{"value":"Введение","anchor":"#введение"}]}}]}},"relatedCategory":{"id":"0187875dbb1b481c81139d0a2234656b","title":"python","path":"/category/python/","related":[{"id":"mobile","path":"/category/mobile/","title":"mobile"},{"id":"api","path":"/category/api/","title":"api"},{"id":"ui","path":"/category/ui/","title":"ui"}]}},"context":{}}